iot_gh/AirTable.py
iot_gh/GHAnalogService.py
iot_gh/GHBuzzer.py
iot_gh/GHConf.py
iot_gh/GHFan.py
iot_gh/GHLamps.py
iot_gh/GHServo.py
iot_gh/GHSwitches.py
iot_gh/GHTempSensor.py
iot_gh/GHTemperature.py
iot_gh/GHTextingService.py
iot_gh/GHWebService.py
iot_gh/GHgpio.py
iot_gh/Greenhouse.py
iot_gh/GreenhouseService.py
iot_gh/_IoTGreenhouseService.py
iot_gh/__init__.py
iot_gh-3.0.3.dist-info/LICENSE.txt
iot_gh-3.0.3.dist-info/METADATA
iot_gh-3.0.3.dist-info/WHEEL
iot_gh-3.0.3.dist-info/top_level.txt
iot_gh-3.0.3.dist-info/RECORD
