Metadata-Version: 2.1
Name: iot-gh
Version: 3.0.3
Summary: IoT Greenhouse service
Author-email: K2Controls <keith@k2controls.net>
Project-URL: Homepage, https://github.com/k2controls/iot_gh
Project-URL: Bug Tracker, https://github.com/k2controls/iot_gh/issues
Classifier: Programming Language :: Python :: 3
Classifier: License :: OSI Approved :: MIT License
Classifier: Operating System :: OS Independent
Requires-Python: >=3.7
License-File: LICENSE.txt
